aeda/car/__init__.py
aeda/car/main.py
aeda_data-0.0.1.dist-info/METADATA
aeda_data-0.0.1.dist-info/WHEEL
aeda_data-0.0.1.dist-info/RECORD
