Metadata-Version: 2.1
Name: aeda-data
Version: 0.0.1
Summary: Aeda car API
Project-URL: Homepage, https://github.com/pypa/aeda
Project-URL: Bug Tracker, https://github.com/pypa/aeda/issues
Author-email: Sven Haadem <sven@aeda.no>
Classifier: License :: OSI Approved :: MIT License
Classifier: Operating System :: OS Independent
Classifier: Programming Language :: Python :: 3
Requires-Python: >=3.7
Requires-Dist: requests
